dahel.py
dahel-0.1.0.dist-info/LICENSE
dahel-0.1.0.dist-info/WHEEL
dahel-0.1.0.dist-info/METADATA
dahel-0.1.0.dist-info/RECORD
